odoo10_addon_base_country_state_translatable-10.0.1.0.0-py2.7-nspkg.pth
odoo/addons/base_country_state_translatable/README.rst
odoo/addons/base_country_state_translatable/__init__.py
odoo/addons/base_country_state_translatable/__manifest__.py
odoo/addons/base_country_state_translatable/models/__init__.py
odoo/addons/base_country_state_translatable/models/res_country.py
odoo10_addon_base_country_state_translatable-10.0.1.0.0.dist-info/DESCRIPTION.rst
odoo10_addon_base_country_state_translatable-10.0.1.0.0.dist-info/METADATA
odoo10_addon_base_country_state_translatable-10.0.1.0.0.dist-info/RECORD
odoo10_addon_base_country_state_translatable-10.0.1.0.0.dist-info/WHEEL
odoo10_addon_base_country_state_translatable-10.0.1.0.0.dist-info/metadata.json
odoo10_addon_base_country_state_translatable-10.0.1.0.0.dist-info/namespace_packages.txt
odoo10_addon_base_country_state_translatable-10.0.1.0.0.dist-info/top_level.txt
